pymetaterp/__init__.py
pymetaterp/boot.py
pymetaterp/boot_compiled.py
pymetaterp/boot_grammar.py
pymetaterp/boot_stackless.py
pymetaterp/boot_tree.py
pymetaterp/python.py
pymetaterp/python_compiled.py
pymetaterp/python_grammar.py
pymetaterp/util.py
pymetaterp-1.1.dist-info/METADATA
pymetaterp-1.1.dist-info/WHEEL
pymetaterp-1.1.dist-info/top_level.txt
pymetaterp-1.1.dist-info/RECORD
