Metadata-Version: 2.1
Name: pymetaterp
Version: 1.1
Summary: A python parser that builds python ASTs in 502 lines of python without using modules
Home-page: https://github.com/asrp/pymetaterp
Author: asrp
Author-email: asrp@email.com
License: UNKNOWN
Keywords: parser peg python minimal
Platform: UNKNOWN
